LICENSE.txt
MANIFEST.in
README.rst
setup.py
clapperboard/__init__.py
clapperboard/crop.py
clapperboard/sync.py
clapperboard.egg-info/PKG-INFO
clapperboard.egg-info/SOURCES.txt
clapperboard.egg-info/dependency_links.txt
clapperboard.egg-info/entry_points.txt
clapperboard.egg-info/requires.txt
clapperboard.egg-info/top_level.txt