Metadata-Version: 1.1
Name: clapperboard
Version: 0.2
Summary: A command-line clapperboard
Home-page: https://github.com/sdeleon28/clapperboard
Author: Santiago de Leon
Author-email: sdeleon28@gmail.com
License: MIT
Download-URL: https://github.com/sdeleon28/clapperboard/tarball/0.2
Keywords: movie clip video clapperboard editing
Platform: UNKNOWN
Classifier: Development Status :: 3 - Alpha
Classifier: Intended Audience :: Developers
Classifier: License :: OSI Approved :: MIT License
Classifier: Programming Language :: Python :: 2
Classifier: Programming Language :: Python :: 2.7
Classifier: Programming Language :: Python :: 3
Classifier: Programming Language :: Python :: 3.3
Classifier: Programming Language :: Python :: 3.4
Classifier: Programming Language :: Python :: 3.5
